EmailListener/EmailListener.py
EmailListener/__init__.py
EmailListener/errors.py
EmailListener/types.py
IMAP_EmailListener-1.0.0.dist-info/LICENSE
IMAP_EmailListener-1.0.0.dist-info/METADATA
IMAP_EmailListener-1.0.0.dist-info/WHEEL
IMAP_EmailListener-1.0.0.dist-info/top_level.txt
IMAP_EmailListener-1.0.0.dist-info/RECORD
