Metadata-Version: 2.1
Name: IMAP-EmailListener
Version: 1.0.0
Summary: Библиотека для прослушивания и обработки электронных писем через IMAP.
Home-page: https://github.com/vo0ov/IMAP-EmailListener
Author: vo0ov
Author-email: artgr123@yandex.ru
Classifier: Programming Language :: Python :: 3
Classifier: License :: OSI Approved :: MIT License
Classifier: Operating System :: OS Independent
Requires-Python: >=3.6
License-File: LICENSE
Requires-Dist: beautifulsoup4>=4.9.3
